README.md
setup.py
mttkinter/__init__.py
mttkinter/mtTkinter.py
mttkinter.egg-info/PKG-INFO
mttkinter.egg-info/SOURCES.txt
mttkinter.egg-info/dependency_links.txt
mttkinter.egg-info/top_level.txt