Metadata-Version: 1.1
Name: mttkinter
Version: 0.6.1
Summary: A thread-safe wrapper around Tkinter for Python
Home-page: https://github.com/RedFantom/mtTkinter
Author: mtTkinter authors
Author-email: redfantom@outlook.com
License: LGPLv3
Download-URL: https://github.com/RedFantom/mtTkinter/releases
Keywords: tkinter,threading
Platform: UNKNOWN
Classifier: License :: OSI Approved :: GNU Lesser General Public License v3 (LGPLv3)
